mw_jsons/__init__.py
mw_jsons/data_sink_course.py
mw_jsons/data_sink_departament.py
mw_jsons/data_sink_subject.py
mw_jsons/data_source_departament.py
mw_jsons/data_source_subject.py
mw_jsons/filters.py
mw_jsons/main.py
mw_jsons/models.py
mw_jsons/pipe.py
mw_jsons-0.0.2.dist-info/METADATA
mw_jsons-0.0.2.dist-info/RECORD
mw_jsons-0.0.2.dist-info/WHEEL
mw_jsons-0.0.2.dist-info/entry_points.txt
mw_jsons-0.0.2.dist-info/top_level.txt
