Metadata-Version: 2.1
Name: mw-jsons
Version: 0.0.2
Summary: WebCrawler for genarating MatriculaWeb data
Home-page: https://github.com/matwebapi/mwapi
Author: Marlon Mendes
Author-email: marlonciriatico@gmail.com
License: UNKNOWN
Platform: UNKNOWN
Classifier: Programming Language :: Python :: 3
Classifier: License :: OSI Approved :: MIT License
Classifier: Operating System :: OS Independent
